mercurytest/mercury_filter.py
mercurytest-0.0.1.dist-info/METADATA
mercurytest-0.0.1.dist-info/WHEEL
mercurytest-0.0.1.dist-info/top_level.txt
mercurytest-0.0.1.dist-info/RECORD
